mergedapi/__init__.py
mergedapi/api_helper.py
mergedapi/configuration.py
mergedapi/mergedapi_client.py
mergedapi/controllers/__init__.py
mergedapi/controllers/administration_controller.py
mergedapi/controllers/alert_controller.py
mergedapi/controllers/api_controller.py
mergedapi/controllers/attestation_controller.py
mergedapi/controllers/authentication_controller.py
mergedapi/controllers/base_controller.py
mergedapi/controllers/bom_component_controller.py
mergedapi/controllers/bom_controller.py
mergedapi/controllers/bom_license_controller.py
mergedapi/controllers/bom_whitelist_controller.py
mergedapi/controllers/checklist_controller.py
mergedapi/controllers/checklist_template_controller.py
mergedapi/controllers/compliance_document_controller.py
mergedapi/controllers/compliance_scan_controller.py
mergedapi/controllers/configuration_controller.py
mergedapi/controllers/data_store_controller.py
mergedapi/controllers/debug_controller.py
mergedapi/controllers/device_controller.py
mergedapi/controllers/documentation_controller.py
mergedapi/controllers/facts_controller.py
mergedapi/controllers/instance_schedule_state_controller.py
mergedapi/controllers/integrity_sku_controller.py
mergedapi/controllers/integrity_software_product_controller.py
mergedapi/controllers/inventory_controller.py
mergedapi/controllers/license_controller.py
mergedapi/controllers/logs_controller.py
mergedapi/controllers/organization_controller.py
mergedapi/controllers/schedule_controller.py
mergedapi/controllers/scoring_factor_controller.py
mergedapi/controllers/scoring_plan_controller.py
mergedapi/controllers/scoring_score_controller.py
mergedapi/controllers/scoring_value_report_controller.py
mergedapi/controllers/services_controller.py
mergedapi/controllers/snapshot_controller.py
mergedapi/controllers/system_controller.py
mergedapi/controllers/tenant_controller.py
mergedapi/controllers/utility_controller.py
mergedapi/controllers/version_controller.py
paragon_sdk-1.0.0.dist-info/LICENSE
paragon_sdk-1.0.0.dist-info/METADATA
paragon_sdk-1.0.0.dist-info/WHEEL
paragon_sdk-1.0.0.dist-info/top_level.txt
paragon_sdk-1.0.0.dist-info/RECORD
