Metadata-Version: 2.1
Name: paragon-sdk
Version: 1.0.0
Summary: Paragon Automation APIs
Author-email: sanchetiv <sanchetiv@juniper.net>
Project-URL: Documentation, https://www.juniper.net/documentation/product/us/en/juniper-paragon-automation/
Requires-Python: >=3.7
License-File: LICENSE
Requires-Dist: apimatic-core ~=0.2.0
Requires-Dist: apimatic-core-interfaces ~=0.1.0
Requires-Dist: apimatic-requests-client-adapter ~=0.1.0
Requires-Dist: python-dateutil ~=2.8.1
Provides-Extra: testutils
Requires-Dist: pytest >=7.2.2 ; extra == 'testutils'
